{
  "cursos": {
    "curso": "string",
    "codigo": "number",
    "id": "number",
    "activo": "boolean",
    "area": "string",
    "sede": "string",
    "año": "number",
    "inicio": "date",
    "inscripcion": "boolean",
    "fin": "date",
    "cierre_inscripcion": "date",
    "duracion": "string",
    "dias": "object",
    "horario": "string",
    "idProfesor": "number",
    "profesor": "string",
    "descripcion": "string",
    "titulo": "string",
    "modalidad": "string",
    "requisitos": "object",
    "temario": "object"
  },
  "cursos_required": {
    "curso": true,
    "codigo": true,
    "id": true,
    "activo": true,
    "area": true,
    "sede": true,
    "año": true,
    "inicio": true,
    "inscripcion": true,
    "fin": true,
    "cierre_inscripcion": true,
    "duracion": true,
    "dias": false,
    "horario": true,
    "idProfesor": false,
    "profesor": true,
    "descripcion": true,
    "titulo": true,
    "modalidad": true,
    "requisitos": false,
    "temario": false
  },
  "requisitos": [
    "Ser mayor de 18 años",
    "Presentar DNI vigente",
    "Presentar titulo primario/secundario completo"
  ]
}